<?xml version="1.0" encoding="utf-8" ?>
<dwsync>
<file name="Miscelaneos-2.jpg" server="ftp.ziurfreelance.com//public_html/" local="131779915980000000" remote="131780725200000000" Dst="0" />
<file name="Miscelaneos-3.jpg" server="ftp.ziurfreelance.com//public_html/" local="131779916630000000" remote="131780725200000000" Dst="0" />
<file name="Miscelaneos-4.jpg" server="ftp.ziurfreelance.com//public_html/" local="131779916880000000" remote="131780725200000000" Dst="0" />
<file name="Miscelaneos-5.jpg" server="ftp.ziurfreelance.com//public_html/" local="131779917140000000" remote="131780725200000000" Dst="0" />
<file name="Miscelaneos-6.jpg" server="ftp.ziurfreelance.com//public_html/" local="131779917300000000" remote="131780725200000000" Dst="0" />
<file name="Miscelaneos-7.jpg" server="ftp.ziurfreelance.com//public_html/" local="131779917300000000" remote="131780725200000000" Dst="0" />
<file name="Miscelaneos-8.jpg" server="ftp.ziurfreelance.com//public_html/" local="131779917600000000" remote="131780725200000000" Dst="0" />
<file name="Miscelaneos-1.jpg" server="C:/wamp64/www/ziurfreelance2/" local="131779915840000000" remote="131779915840000000" Dst="0" />
<file name="Miscelaneos-2.jpg" server="C:/wamp64/www/ziurfreelance2/" local="131779915980000000" remote="131779915980000000" Dst="0" />
<file name="Miscelaneos-3.jpg" server="C:/wamp64/www/ziurfreelance2/" local="131779916630000000" remote="131779916630000000" Dst="0" />
<file name="Miscelaneos-4.jpg" server="C:/wamp64/www/ziurfreelance2/" local="131779916880000000" remote="131779916880000000" Dst="0" />
<file name="Miscelaneos-5.jpg" server="C:/wamp64/www/ziurfreelance2/" local="131779917140000000" remote="131779917140000000" Dst="0" />
<file name="Miscelaneos-6.jpg" server="C:/wamp64/www/ziurfreelance2/" local="131779917300000000" remote="131779917300000000" Dst="0" />
<file name="Miscelaneos-7.jpg" server="C:/wamp64/www/ziurfreelance2/" local="131779917300000000" remote="131779917300000000" Dst="0" />
<file name="Miscelaneos-8.jpg" server="C:/wamp64/www/ziurfreelance2/" local="131779917600000000" remote="131779917600000000" Dst="0" />
<file name="Miscelaneos-1.jpg" server="ftp.ziurfreelance.com//public_html/" local="131779915840000000" remote="131780725200000000" Dst="0" />
<file name="Miscelaneos-1.jpg" server="E:/wamp64/www/ziurfreelance2/" local="131779915840000000" remote="131779915840000000" Dst="0" />
<file name="Miscelaneos-2.jpg" server="E:/wamp64/www/ziurfreelance2/" local="131779915980000000" remote="131779915980000000" Dst="0" />
<file name="Miscelaneos-3.jpg" server="E:/wamp64/www/ziurfreelance2/" local="131779916630000000" remote="131779916630000000" Dst="0" />
<file name="Miscelaneos-4.jpg" server="E:/wamp64/www/ziurfreelance2/" local="131779916880000000" remote="131779916880000000" Dst="0" />
<file name="Miscelaneos-5.jpg" server="E:/wamp64/www/ziurfreelance2/" local="131779917140000000" remote="131779917140000000" Dst="0" />
<file name="Miscelaneos-6.jpg" server="E:/wamp64/www/ziurfreelance2/" local="131779917300000000" remote="131779917300000000" Dst="0" />
<file name="Miscelaneos-7.jpg" server="E:/wamp64/www/ziurfreelance2/" local="131779917300000000" remote="131779917300000000" Dst="0" />
<file name="Miscelaneos-8.jpg" server="E:/wamp64/www/ziurfreelance2/" local="131779917600000000" remote="131779917600000000" Dst="0" />
<file name="Miscelaneos-1.jpg" server="E:/wamp64/www/ziurfreelance/" local="131779915840000000" remote="131779915840000000" Dst="0" />
<file name="Miscelaneos-2.jpg" server="E:/wamp64/www/ziurfreelance/" local="131779915980000000" remote="131779915980000000" Dst="0" />
<file name="Miscelaneos-3.jpg" server="E:/wamp64/www/ziurfreelance/" local="131779916630000000" remote="131779916630000000" Dst="0" />
<file name="Miscelaneos-4.jpg" server="E:/wamp64/www/ziurfreelance/" local="131779916880000000" remote="131779916880000000" Dst="0" />
<file name="Miscelaneos-5.jpg" server="E:/wamp64/www/ziurfreelance/" local="131779917140000000" remote="131779917140000000" Dst="0" />
<file name="Miscelaneos-6.jpg" server="E:/wamp64/www/ziurfreelance/" local="131779917300000000" remote="131779917300000000" Dst="0" />
<file name="Miscelaneos-7.jpg" server="E:/wamp64/www/ziurfreelance/" local="131779917300000000" remote="131779917300000000" Dst="0" />
<file name="Miscelaneos-8.jpg" server="E:/wamp64/www/ziurfreelance/" local="131779917600000000" remote="131779917600000000" Dst="0" />
</dwsync>